{
	"#example-face-code": "/faces/example-path.jpg",

	"#breakingnews": "/faces/newspapersmack.gif",
	"#brofist": "/faces/takebrofist.gif",
	"#cokemasterrace": "/faces/yuibrospit.gif",
	"#curious": "/faces/curious.gif",
	"#evilgrin": "/faces/evilgrin.gif",
	"#fedup": "/faces/Fd0u5n.gif",
	"#flattered": "/faces/eririrblush.gif",
	"#flyingbunsofdoom": "/faces/akarisurprise.gif",
	"#forgotkeys": "/faces/gintamaoutlines.gif",
	"#garlock": "/faces/nanamiwink.gif",
	"#giveuponlife": "/faces/giveuponlife.gif",
	"#helmetbro": "/faces/gundamthumbsup.gif",
	"#idoruwinkdesu": "/faces/shinomiyawink.gif",
	"#justno": "/faces/yokosquint.gif",
	"#missedthepoint": "/faces/febrietroll.gif",
	"#hajimepout": "",
	"#nuidideverythingright": "/faces/nuitongue.gif",
	"#rerorero": "/faces/rerorero.gif",
	"#scrumptiouslymoe": "/faces/soranodeliciousness.gif",
	"#slapbet": "/faces/akarislap.gif",
	"#watchadoin": "/faces/hyoukawatchadoin.gif",
	"#torrentialdownpour": "/faces/makotears.gif",
	"#slightoverreaction": "/faces/tooexcited.gif",
	"#prelenny": "/faces/licklips.gif",
	"#volibearQ": "/faces/volibearq.gif",
	"#mywaifumadeyouasandwich": "/faces/asunasandwich.gif",
	"#urbansmile": "",
	"#anko": "",
	"#hyoukawink": "",
	"#yousaidsomethingdumb": "",
	"#banjo": "",
	"#peasants": "",
	"#excitedyui": "",
	"#dancewithit": "/faces/dealwithitkumin.gif"


}
